webgraphics/__init__.py
webgraphics/graphics.py
webgraphics/webgraphics.py
webgraphics-0.0.3.dist-info/METADATA
webgraphics-0.0.3.dist-info/WHEEL
webgraphics-0.0.3.dist-info/top_level.txt
webgraphics-0.0.3.dist-info/RECORD
