Metadata-Version: 2.1
Name: webgraphics
Version: 0.0.3
Summary: a package to allow python users to create graphics programs that can run in a browser (on the web)
Author: Chris Piech
License: UNKNOWN
Platform: UNKNOWN
